{"stats": {"name": "CHSRC - Sign of the Bellbird", "date": "Thu Mar 24, 2022", "uphill": 263, "downhill": 274, "distance": 6301.14, "duration": 4171, "pace": 5.439, "polyline": "nueiGcvt|_@??NKT?@?P@D@B@@@FBD@B@F@BBHFDBJHB?H@B?J?DAB?HAJEBAPKDE@AFEBABA@C@ADE@ADEBCDETS@CJSBIJ_@DQLSFODGJQTYBAXCF?B?NDXNFBHFB@D@DB@?HBFD@BBBLFJFB@NJ@@VN\\FL?LCX?\\JD@LF@@NJD@B@B@\\L@BFFFDNAD@?B?@?B?B?@C????????@????????????@?LAf@CN?B?XHRDJFNDD@B@RFRDD@TFTADAT@HAB@H?D?RAVITKT?D@NFFDBBPNJFJDLJLJ@DFFLJ@DDBJLHDBBHBHBD?B@H@J?NAFHb@XXPZJLBF?B@D?B?@?D?H?H@B?@AJG@?DA@?DAB?F?BAHEJ@@AFAD@FH?DBDBBAFEJ?V@D@R@R?T?DDZFDFDH\\@DFN@DDPL\\AR?F?LBR@DDREJA`@CHCLCRCVAFERCBGREXEh@?J?LI^K`@AFE`@EJQVIN?R?FAf@@FAVERIb@?DA@?C?A???????????@????????????A??A???@????@A@C??CXEXANAF?L?J@N?H?RAB@D?P@H?H@BBF@?B@D?B@D@D@@@J?JAD@F@@B?FALAFGREVERERADAJKb@B\\?B@V@JBH@H@BDJ@P@V@VC^AD?RAF?HCRADCNCL?D?L?BBF@@@FBJBHJLHDHHDBH@DFHFNHJDFHJFPLHBZLBBJF@D@D?BCA??A???AA???????@@A??????A???@?????????CB?A@@????A?????????CPIn@AFAFG\\AFMNMDIDCBGHMPKNQZCBIJKPKNIHSXUTCDUROPCBMLMJCBOHOL?B?LAF@Z@B????A?????@???????@@B?@?LBLBB@D@D?JCJGFIVUTMJCBCNAPGTIBAHEHCLELGHGFCHCFCFEVKPUBEHUBG@ANMB?LCNALCLE@ALGFEDELEFANCB?H?R?B@F?B?@??A?ABK@G?E@EDI@O@GACACAE@E?E?K?A?C?GBM@IFK@?@CDEBCR_@\\UHE@??@A@A?@CA????@?AA?@??A?????????A?AHBD@FDB@D@L?D?B?@?B?@??@D@LC@AHCNKBEFIFGBCDEFEDCDC?C@C@EDKJCNFB@D?@ADCFAD?F?@ABA@ADGLCD@B@D@@?BBDDD?@?@??@F?DAFCJCB?BFL?@?B?@?@CB@F@D?B?D?BEB@PBD?\\HFF@@DBLAB@HH?DB?DADEDD?@A@BIABABA@?@@@ACDGD?A?AF?JAI?AAEDAC@D?@E?C?EDA@CDE??@@D?F?@@DB@?B@B?FAB@B?B?D?F@F?@?@@@@DBD@HD@@@BDEBAHEB?@?HABB@@B?HCBALE??H?LFL@D@DDHFHHB?F?HEDCFEDCBAP@DA@?@E??@@A?CCBAD?B@@?BABEBABCFCHAH?HBBC@ATGLCJCHCRIBCFGB?F@PHBBMM??AC?W?E?EAE?CACAAACACACAE?C@C@C?ADM@GACAAGAG?M?G@C?A?GCE@A@CBMLQHM@A?E?IDMDYGGGGMOMEAQAWAI@IDI@AAC?CAGAC?OFW@K@CIGGCCCAQOI?a@Fc@BE@WNMBACKGOMACEUAC?@????@????????????????????????A?A@?????A???AA??AACA?@IOSi@MGIGMIGGQKC?CCGKOSAEMe@ACC_@EAAEC?GAE@EDIDEDGDE@A?A???A@C@C@CFG@AE@BA@GAID@HB@@AAAAAAABA@A?KEY?QGUCGC_@?M?EC]AEMa@Q[EAKICCEGEEE@E?ICQGC?ECMGICEAMCE?QGAAEEICGDMFCBKDCDGHMHIBO@C@EBA?AA???@??????????FACLAICA?BADAA?BA@??@??F@BF??AA?C@IAMCKGG@IJIHE?C?G?C@INC@C@?@?@C@M?C@E@CBCBEBA?KBQ@G@OFIHMBEAOEGAOMCCK][SU@WCE?GBSBA@EAGCE?O?GCK?SEGGAK?Q@e@?E?Y@GAUBSJs@@EHi@@U@M?O?EB]?O@ODEDGPQFMB[?E@CDK@GH[Bc@@A@?IKDc@Fe@@E@CDU?EFY@K?G@E@GAI?EB[AEGi@?E@W?EGYCEAEIUGGEY?CGMECCCCOA]Ag@C[?IDQ?CGYCEEAC?SHKFKFC@A@G@KDC?GAEAK?I?IACBE?C?MEKGECa@SC?AAAA?CAA????????????@??????????@??@@AA@A??????@?????????????IIIGMKC?GBC@KAAAGAAAG?EAC?EAGAECIEAACACEEECECACCMMCEEGGGQOIGIGKICAYMI?G?C@EBGBWFYBC?K?M@G?G?K?K?E@M?I?CACA_@KCA_@SQMOGc@KC?IAa@KAE??A?C?G?UQc@SKCUMQGOEKAQ@g@@g@OMESMKIOGQGKCGAMIOIEASGM?a@LONKRKL??CB?A?A????AFCFCFSr@O`@ABCDYXa@\\CBGDIFULI@IAQ?I@EAOIGGCCOQQIEAEAO?KBGFA@CBC@A@@@A??@?????????????@???????C?@"}}