{"stats": {"name": "Picking up the car", "date": "Sun Oct 24, 2021", "uphill": 333, "downhill": 249, "distance": 22483.04, "duration": 3476, "pace": 23.285, "polyline": "tc~hGiklr_@@@DDDLFNJNNNH@F@P?RCPCj@EHANIDEPYFMBEFQ@M@G?Q?C?CGMAEGQCGCEGEGCCCCCCCICCAGCECAACAECECCAAAKKEEGGGMCGACM[AWAK?E?I?I@G?EDUDQDKDQJSDKLYDIDKHSHODKHSBIDIHUJSDQJUBKDQFa@BK@GBQ?GDSB[?EBMBMFYBKBEFYFY@EHWFYH_@DSBEDQF[BSF_@@GBQHc@BYDYBMDYB[BMDY@MB]Dc@@GBUDi@D]Fu@@ILqAHkAD_@Dw@FaABa@Fq@?IB_@Bk@DaA@a@Fy@Fe@HoA?k@Cm@AOA{AFs@Jw@BSHe@Hg@BSBSPiCBa@D_ADc@Fc@PaADOb@mBBODONk@ZcADIVk@DGJQd@s@DG`@q@JOHMV[DE^a@XYRQPQ^_@^_@DGt@w@bAkAl@q@b@g@z@cA`@g@z@cAzAaB|AoAd@a@`BwANMtAsAxAwALMj@i@`AaAtA{A|AeBJMnAsARS`@c@LMTUPWBGDGBEFQJ[D]Ju@Hk@@KDUHa@XsAZ}ABMDMd@qBXcAVu@HYTs@Pe@\\aAf@}AJ[t@gCNe@XaAJYH[^qA`@_BH[b@qBXaAXaATu@j@cBt@iCv@kCDODOl@wBDORk@j@oBt@iCFQz@mCPg@Rk@Tk@Ro@Tm@~@qCRq@r@qBpA{BLO|@{@p@eAPi@No@b@qCPgA`@uBNm@FUx@uCPm@r@kCHWRo@Tq@Rq@HYv@oC\\iAZgAv@kCPi@v@sCFSh@oBVgALa@DOJa@T_AJ]ZgAVw@DM|@}BFMDMt@mBXu@l@_B`AmCFQ^eAx@wBbAmCNa@FQN_@v@uBz@_CDMDMd@oARg@HWZy@HUTm@Nc@DKz@cCFM|@aCNa@L_@HSBIPg@DGZ{@L_@r@qBVu@DIZ{@L_@\\cA\\iARq@n@yBDM^kA|@mCX{@Rk@J]x@iCJYJW\\{@JWPc@d@mAb@mBF[TwA\\{At@kCNm@BMNeADeA@]?MFeC?M@OBgADgA?MDaA@o@@K?K@K@q@@K?K?s@Cq@AMEe@Eu@C]Gm@AOAQM_BEg@Gk@IeAEm@GiAGkAEu@EsACy@?]Cy@A_@A]?]A_@@]@{@@]B]B[D]J{@PwAJ{@L{@N{AB_@Da@Da@Dc@Bc@HcAReCR{BVsCB[PoBPuBN_BD_@J_AB]RiBPeBHu@Fu@D[N{ABSNsAJ_AL_AFQFQVq@ZiAFe@JoAJgA@]BY@W@I?KB_@Ba@?IFw@@I@KBYHk@JwAJ_D@S?SBqAF{BFaABSZwCHuA?U?i@BaADg@Bg@Dg@LoAFc@Fu@@QDc@XsBVoALs@V{BZaBd@iCTaDN{AFc@Da@Fc@Fq@Bc@Bg@FaABa@@Q@OVeCDcB@k@@yA?m@RcDX{ARaA`@uB\\uBJyB?q@EuCBqCVqBRaAVyAHm@PuBLuBPcDBWDo@L{BDq@Fo@@YFq@NaB^qCHo@b@sCLiANuC@YJkD@WBq@FuC?WO}COmBKsAAYGw@UcDEs@CYGu@OaCMkBU{CMgBGw@M_BCWQcCQmCIaDDcD?UF{C?WDeD@o@EiDAYKeDA]Ay@A}@?{@?{@?}@?_AA_AA}AKwAWaCUaBGq@Gs@Is@Go@G}@Eq@CeDPaDJoABsA?[MoAKq@_@yBSoCAUM}CCm@EaAEyAAm@GoBAQIyBIcDCo@IkCIaDCcAAk@KyCAi@AUK_DAe@GoBA{A@u@NmB@QZeCHc@XmBBSTaBNkA^{CBQ^wCJw@VmBNgAXyAXqAPaAHq@B]?O@OCiAEy@Gu@OcCEi@AYEs@?M?[?K@g@@YNwA@KV}ABK\\mB\\iBBMZkBLuBC}@I_AKeACUCUKw@Io@MaBAOMoA_@uAq@sAEIKUWc@O[Se@[aAOm@AKOsA?KAyB?o@@m@@mA?I?W?a@@e@?M@sB?O?c@@w@@SBg@FiADw@RyCJgARiCLuC@Q@SGgCIiAGa@CQCQI_@Ga@Kq@COK}BAg@IkCMcBQoBGu@Gc@OuAAQEa@Iq@Es@IuCAeBAcB?a@BuBD}@@SD{@NsBJmAHqAFgA@UPuCBc@@OHqA@O@SBe@Be@@QPqCBk@NiCFoABm@@W@W@o@@WAW?q@KoBGeACWCWAWGm@Gk@AQCUGm@IsAAUAc@EcBC{@EkAGuBEmAAQAa@IiCAS?OCi@ASAw@As@C}@MWIEKCWEo@MsA[SGUCSCe@Mm@OOEw@SUEOCEAk@OEAe@Kc@KICg@K]KIAIC}@QICICGAiAWy@S]GQGkA[{@Ui@Ma@M_@IICUE{@Oa@IoAUa@K{@S_BQo@JKBWJc@Re@RKDe@Re@PWLc@N_@PKBq@X_@Ns@`@EBIFYV]^UTGFo@n@GBa@TOHcAT{ALG@yALs@LYBg@Jm@JI@e@Jq@LSDG@G@E@UD[FMDG?E@G@G@[FKBMBMBSBYFMBE?_@HYDMBKBi@H[FSBMBMBYDWFk@Hs@LSBKB]FQDWDE@SBG@w@NG@]Fe@JSDm@JKBe@Js@LE@OBE@E@K@WFE?MBKBSDk@JE@m@JG@QDaANE@aAN}@NE@i@Ja@FSDs@LSBG@c@HYFa@HMBw@PSFYHUFMDYNMFE@MFs@`@OHKDWNGBEDQHKHSHEBYPEBEBKFMDMFKHKFKF]RKDEBEDWLQJEDEBEBIFe@VGBw@f@GBQJYRYPSNEBEDMHWP]Vc@\\KHQLEBEBIH]VIFKHe@\\CBEBQPSJEDKFo@h@SNIHKHQNIJCDIJILWPa@^GHKV?HAD??"}}